<?xml version="1.0" encoding="utf-8" ?>
<dwsync>
<file name="validateEmail01.jsf" server="C:/DevelopingJSFComponents/apache-tomcat-6.0.14/wtpwebapps/7627_02_Examples/" local="128926681981513000" remote="128926681980000000" />
<file name="validateRegExpr01.jsf" server="C:/DevelopingJSFComponents/apache-tomcat-6.0.14/wtpwebapps/7627_02_Examples/" local="128931463389834662" remote="128931463380000000" />
<file name="validateEqual01.jsf" server="C:/DevelopingJSFComponents/apache-tomcat-6.0.14/wtpwebapps/7627_02_Examples/" local="128931463812216896" remote="128931463810000000" />
<file name="inputDate01.jsf" server="C:/DevelopingJSFComponents/apache-tomcat-6.0.14/wtpwebapps/7627_02_Examples/" local="128926682070143000" remote="128926682070000000" />
<file name="inputDate02.jsf" server="C:/DevelopingJSFComponents/apache-tomcat-6.0.14/wtpwebapps/7627_02_Examples/" local="128926682021593000" remote="128926682020000000" />
<file name="inputCalendar01.jsf" server="C:/DevelopingJSFComponents/apache-tomcat-6.0.14/wtpwebapps/7627_02_Examples/" local="128931353377220000" remote="128931353370000000" />
<file name="schedule01.jsf" server="C:/DevelopingJSFComponents/apache-tomcat-6.0.14/wtpwebapps/7627_02_Examples/" local="128929578090790000" remote="128929578090000000" />
<file name="inputFileUpload01.jsf" server="C:/DevelopingJSFComponents/apache-tomcat-6.0.14/wtpwebapps/7627_02_Examples/" local="128926743547273000" remote="128926743540000000" />
<file name="tree2_01.jsf" server="C:/DevelopingJSFComponents/apache-tomcat-6.0.14/wtpwebapps/7627_02_Examples/" local="128926800767983000" remote="128926800760000000" />
<file name="tree01_2.jsf" server="C:/DevelopingJSFComponents/apache-tomcat-6.0.14/wtpwebapps/7627_02_Examples/" local="128927944291720000" remote="128927944290000000" />
<file name="tree01_1.jsf" server="C:/DevelopingJSFComponents/apache-tomcat-6.0.14/wtpwebapps/7627_02_Examples/" local="128926802298173000" remote="128926802290000000" />
<file name="tree01_3.jsf" server="C:/DevelopingJSFComponents/apache-tomcat-6.0.14/wtpwebapps/7627_02_Examples/" local="128926859176060000" remote="128926859170000000" />
<file name="security01.jsf" server="C:/DevelopingJSFComponents/apache-tomcat-6.0.14/wtpwebapps/7627_02_Examples/" local="128926859781890000" remote="128926859780000000" />
<file name="dataList03.jsf" server="C:/DevelopingJSFComponents/apache-tomcat-6.0.14/wtpwebapps/7627_02_Examples/" local="128927569675331000" remote="128927569670000000" />
<file name="panelNavigation01.jsf" server="C:/DevelopingJSFComponents/apache-tomcat-6.0.14/wtpwebapps/7627_02_Examples/" local="128931546690753921" remote="128931546690000000" />
<file name="index.jsf" server="C:/DevelopingJSFComponents/apache-tomcat-6.0.14/wtpwebapps/7627_02_Examples/" local="128931273618900000" remote="128931273610000000" />
<file name="about.jsf" server="C:/DevelopingJSFComponents/apache-tomcat-6.0.14/wtpwebapps/7627_02_Examples/" local="128931390835220000" remote="128931390830000000" />
<file name="contact.jsf" server="C:/DevelopingJSFComponents/apache-tomcat-6.0.14/wtpwebapps/7627_02_Examples/" local="128931275878830000" remote="128931275870000000" />
<file name="products.jsf" server="C:/DevelopingJSFComponents/apache-tomcat-6.0.14/wtpwebapps/7627_02_Examples/" local="128931469686864302" remote="128931469680000000" />
<file name="services.jsf" server="C:/DevelopingJSFComponents/apache-tomcat-6.0.14/wtpwebapps/7627_02_Examples/" local="128931286876090000" remote="128931286870000000" />
<file name="panelNavigation2_01.jsf" server="C:/DevelopingJSFComponents/apache-tomcat-6.0.14/wtpwebapps/7627_02_Examples/" local="128931159010000000" remote="128931159010000000" />
<file name="panelNavigation2_02.jsf" server="C:/DevelopingJSFComponents/apache-tomcat-6.0.14/wtpwebapps/7627_02_Examples/" local="128931259792830000" remote="128931259790000000" />
<file name="dataTable01.jsf" server="C:/DevelopingJSFComponents/apache-tomcat-6.0.14/wtpwebapps/7627_02_Examples/" local="128927887004140000" remote="128927887000000000" />
<file name="newspaperTable01.jsf" server="C:/DevelopingJSFComponents/apache-tomcat-6.0.14/wtpwebapps/7627_02_Examples/" local="128931656982674387" remote="128931656980000000" />
<file name="dataScroller01.jsf" server="C:/DevelopingJSFComponents/apache-tomcat-6.0.14/wtpwebapps/7627_02_Examples/" local="128927908143350000" remote="128927908140000000" />
<file name="schedule02.jsf" server="C:/DevelopingJSFComponents/apache-tomcat-6.0.14/wtpwebapps/7627_02_Examples/" local="128930094490610000" remote="128930094490000000" />
<file name="schedule03.jsf" server="C:/DevelopingJSFComponents/apache-tomcat-6.0.14/wtpwebapps/7627_02_Examples/" local="128929237697680000" remote="128929237690000000" />
<file name="schedule04.jsf" server="C:/DevelopingJSFComponents/apache-tomcat-6.0.14/wtpwebapps/7627_02_Examples/" local="128929239075920000" remote="128929239070000000" />
<file name="panelNavigation2_03.jsf" server="C:/DevelopingJSFComponents/apache-tomcat-6.0.14/wtpwebapps/7627_02_Examples/" local="128931236047410000" remote="128931236040000000" />
<file name="orderform.jsf" server="C:/DevelopingJSFComponents/apache-tomcat-6.0.14/wtpwebapps/7627_02_Examples/" local="128933545042110000" remote="128933545040000000" />
<file name="outofstock.jsf" server="C:/DevelopingJSFComponents/apache-tomcat-6.0.14/wtpwebapps/7627_02_Examples/" local="128931459518117529" remote="128931459510000000" />
<file name="panelNavigation02.jsf" server="C:/DevelopingJSFComponents/apache-tomcat-6.0.14/wtpwebapps/7627_02_Examples/" local="128931520254070517" remote="128931520250000000" />
<file name="jscookMenu01.jsf" server="C:/DevelopingJSFComponents/apache-tomcat-6.0.14/wtpwebapps/7627_02_Examples/" local="128931633441294387" remote="128931633440000000" />
<file name="jscookMenu02.jsf" server="C:/DevelopingJSFComponents/apache-tomcat-6.0.14/wtpwebapps/7627_02_Examples/" local="128931633359504387" remote="128931633350000000" />
<file name="about.jsf" server="C:/DevelopingJSFComponents/apache-tomcat-6.0.14/wtpwebapps/7627_03_Web/" local="128982767205810000" remote="128982767200000000" />
<file name="index.html" server="C:/DevelopingJSFComponents/apache-tomcat-6.0.14/wtpwebapps/7627_03_Web/" local="129054272666820000" remote="129054272660000000" />
</dwsync>